genkit/py.typed
genkit/plugins/compat_oai/__init__.py
genkit/plugins/compat_oai/openai_plugin.py
genkit/plugins/compat_oai/typing.py
genkit/plugins/compat_oai/models/__init__.py
genkit/plugins/compat_oai/models/handler.py
genkit/plugins/compat_oai/models/model.py
genkit/plugins/compat_oai/models/model_info.py
genkit/plugins/compat_oai/models/utils.py
genkit/plugins/compat_oai/__init__.py
genkit/plugins/compat_oai/openai_plugin.py
genkit/plugins/compat_oai/typing.py
genkit/plugins/compat_oai/models/__init__.py
genkit/plugins/compat_oai/models/handler.py
genkit/plugins/compat_oai/models/model.py
genkit/plugins/compat_oai/models/model_info.py
genkit/plugins/compat_oai/models/utils.py
genkit_plugin_compat_oai-0.4.0.dist-info/METADATA
genkit_plugin_compat_oai-0.4.0.dist-info/WHEEL
genkit_plugin_compat_oai-0.4.0.dist-info/licenses/LICENSE
genkit_plugin_compat_oai-0.4.0.dist-info/RECORD
